hanna/LICENSE
hanna/VERSION
hanna/__init__.py
hanna/addons.py
hanna/configuration.py
hanna/parameters.py
hanna/tests.py
hanna/utils.py
hanna/physics/__init__.py
hanna/physics/units.py
hanna-0.2.3.dist-info/METADATA
hanna-0.2.3.dist-info/RECORD
hanna-0.2.3.dist-info/WHEEL
hanna-0.2.3.dist-info/top_level.txt
