Metadata-Version: 2.1
Name: hanna
Version: 0.2.3
Summary: Turns your configurations into actions
Home-page: https://gitlab.com/Dominik1123/Hanna
Author: Dominik Vilsmeier
Author-email: dominik.vilsmeier1123@gmail.com
License: BSD-3-Clause
Keywords: configuration,framework
Platform: UNKNOWN
Classifier: Development Status :: 4 - Beta
Classifier: License :: OSI Approved :: BSD License
Classifier: Programming Language :: Python :: 3.6
Classifier: Topic :: Software Development
Requires-Python: >=3.6
Requires-Dist: pyhocon
